[
  { "id": 1, "name": "Harry Potter" },
  { "id": 2, "name": "Darth Vader" },
  { "id": 3, "name": "Albert Einstein" },
  { "id": 4, "name": "Mona Lisa" },
  { "id": 5, "name": "Godzilla" },
  { "id": 6, "name": "Beyonce" },
  { "id": 7, "name": "Sherlock Holmes" },
  { "id": 8, "name": "Cleopatra" },
  { "id": 9, "name": "Spider-Man" },
  { "id": 10, "name": "Taylor Swift" },
  { "id": 11, "name": "The Terminator" },
  { "id": 12, "name": "Frida Kahlo" },
  { "id": 13, "name": "Napoleon Bonaparte" },
  { "id": 14, "name": "Mickey Mouse" },
  { "id": 15, "name": "Oprah Winfrey" },
  { "id": 16, "name": "Shrek" },
  { "id": 17, "name": "Marie Curie" },
  { "id": 18, "name": "James Bond" },
  { "id": 19, "name": "Serena Williams" },
  { "id": 20, "name": "Winston Churchill" },
  { "id": 21, "name": "Indiana Jones" },
  { "id": 22, "name": "Marilyn Monroe" },
  { "id": 23, "name": "Leonardo da Vinci" },
  { "id": 24, "name": "The Statue of Liberty" },
  { "id": 25, "name": "Elvis Presley" },
  { "id": 26, "name": "Wonder Woman" },
  { "id": 27, "name": "Queen Elizabeth II" },
  { "id": 28, "name": "Willy Wonka" },
  { "id": 29, "name": "Barbie" },
  { "id": 30, "name": "The Joker" },
  { "id": 31, "name": "David Bowie" },
  { "id": 32, "name": "The Loch Ness Monster" },
  { "id": 33, "name": "Usain Bolt" },
  { "id": 34, "name": "SpongeBob SquarePants" },
  { "id": 35, "name": "Jane Austen" },
  { "id": 36, "name": "King Kong" },
  { "id": 37, "name": "Rihanna" },
  { "id": 38, "name": "Pikachu" },
  { "id": 39, "name": "Mahatma Gandhi" },
  { "id": 40, "name": "The Mona Lisa" },
  { "id": 41, "name": "Ariana Grande" },
  { "id": 42, "name": "Dracula" },
  { "id": 43, "name": "Stephen Hawking" },
  { "id": 44, "name": "Homer Simpson" },
  { "id": 45, "name": "Amelia Earhart" },
  { "id": 46, "name": "Batman" },
  { "id": 47, "name": "Lady Gaga" },
  { "id": 48, "name": "Yoda" },
  { "id": 49, "name": "Vincent van Gogh" },
  { "id": 50, "name": "The Eiffel Tower" },
  { "id": 51, "name": "Michael Jackson" },
  { "id": 52, "name": "Hermione Granger" },
  { "id": 53, "name": "Nelson Mandela" },
  { "id": 54, "name": "Mario" },
  { "id": 55, "name": "Madonna" },
  { "id": 56, "name": "Chewbacca" },
  { "id": 57, "name": "Rosa Parks" },
  { "id": 58, "name": "Forrest Gump" },
  { "id": 59, "name": "Kanye West" },
  { "id": 60, "name": "The Great Wall of China" },
  { "id": 61, "name": "Katniss Everdeen" },
  { "id": 62, "name": "Pablo Picasso" },
  { "id": 63, "name": "The Little Mermaid" },
  { "id": 64, "name": "Muhammad Ali" },
  { "id": 65, "name": "Wednesday Addams" },
  { "id": 66, "name": "Galileo Galilei" },
  { "id": 67, "name": "Scooby-Doo" },
  { "id": 68, "name": "Billie Eilish" },
  { "id": 69, "name": "The Sphinx" },
  { "id": 70, "name": "Steve Jobs" },
  { "id": 71, "name": "Luke Skywalker" },
  { "id": 72, "name": "Audrey Hepburn" },
  { "id": 73, "name": "The Hulk" },
  { "id": 74, "name": "Simone Biles" },
  { "id": 75, "name": "William Shakespeare" },
  { "id": 76, "name": "Elsa" },
  { "id": 77, "name": "Freddie Mercury" },
  { "id": 78, "name": "The Tooth Fairy" },
  { "id": 79, "name": "Lionel Messi" },
  { "id": 80, "name": "The Queen of Hearts" }
]
